pmr/__init__.py
pmr-2.0.0.dist-info/top_level.txt
pmr-2.0.0.dist-info/METADATA
pmr-2.0.0.dist-info/WHEEL
pmr-2.0.0.dist-info/RECORD
pmr-2.0.0.dist-info/entry_points.txt
pmr-2.0.0.dist-info/DESCRIPTION.rst
pmr-2.0.0.dist-info/metadata.json
