Metadata-Version: 2.0
Name: pmr
Version: 2.0.0
Summary: Process memory-maps-based restarter
Home-page: https://github.com/pantheon-systems/pmr
Author: David Strauss
Author-email: david@davidstrauss.net
License: MIT
Platform: UNKNOWN
Classifier: Development Status :: 5 - Production/Stable
Classifier: Intended Audience :: System Administrators
Classifier: Topic :: Security
Classifier: Topic :: System
Classifier: Environment :: Console
Classifier: License :: OSI Approved :: MIT License
Classifier: Programming Language :: Python :: 3
Classifier: Programming Language :: Python :: 3.3
